catalystwan/ENDPOINTS.md
catalystwan/__init__.py
catalystwan/abstractions.py
catalystwan/api/__init__.py
catalystwan/api/admin_tech_api.py
catalystwan/api/administration.py
catalystwan/api/alarms_api.py
catalystwan/api/api_container.py
catalystwan/api/basic_api.py
catalystwan/api/config_device_inventory_api.py
catalystwan/api/config_group_api.py
catalystwan/api/configuration_groups/parcel.py
catalystwan/api/configuration_groups/parcels/cellular_controller.py
catalystwan/api/dashboard_api.py
catalystwan/api/device_action_api.py
catalystwan/api/feature_profile_api.py
catalystwan/api/logs_api.py
catalystwan/api/monitoring_status_api.py
catalystwan/api/mtt_aaa_api.py
catalystwan/api/omp_api.py
catalystwan/api/packet_capture_api.py
catalystwan/api/parcel_api.py
catalystwan/api/partition_manager_api.py
catalystwan/api/policy_api.py
catalystwan/api/resource_pool_api.py
catalystwan/api/software_action_api.py
catalystwan/api/speedtest_api.py
catalystwan/api/task_status_api.py
catalystwan/api/template_api.py
catalystwan/api/templates/README.md
catalystwan/api/templates/bool_str.py
catalystwan/api/templates/cli_template.py
catalystwan/api/templates/device_template/device_template.py
catalystwan/api/templates/device_template/device_template_payload.json.j2
catalystwan/api/templates/device_variable.py
catalystwan/api/templates/feature_template.py
catalystwan/api/templates/feature_template_field.py
catalystwan/api/templates/feature_template_payload.py
catalystwan/api/templates/models/cisco_aaa_model.py
catalystwan/api/templates/models/cisco_banner_model.py
catalystwan/api/templates/models/cisco_bfd_model.py
catalystwan/api/templates/models/cisco_bgp_model.py
catalystwan/api/templates/models/cisco_logging_model.py
catalystwan/api/templates/models/cisco_ntp_model.py
catalystwan/api/templates/models/cisco_omp_model.py
catalystwan/api/templates/models/cisco_ospf.py
catalystwan/api/templates/models/cisco_ospfv3.py
catalystwan/api/templates/models/cisco_secure_internet_gateway.py
catalystwan-0.41.2.dist-info/LICENSE
catalystwan-0.41.2.dist-info/METADATA
catalystwan-0.41.2.dist-info/WHEEL
catalystwan-0.41.2.dist-info/RECORD
