Metadata-Version: 2.3
Name: catalystwan
Version: 0.41.2
Summary: Cisco Catalyst WAN SDK for Python
Author: kagorski
Author-email: kagorski@cisco.com
Requires-Python: >=3.8.0,<4.0.0
Classifier: Programming Language :: Python :: 3
Classifier: Programming Language :: Python :: 3.8
Classifier: Programming Language :: Python :: 3.9
Classifier: Programming Language :: Python :: 3.10
Classifier: Programming Language :: Python :: 3.11
Classifier: Programming Language :: Python :: 3.12
Classifier: Programming Language :: Python :: 3.13
Requires-Dist: Jinja2 (>=3.1.2,<4.0.0)
Requires-Dist: attrs (>=21.4.0)
Requires-Dist: ciscoconfparse (==1.9.41)
Requires-Dist: clint (>=0.5.1,<0.6.0)
Requires-Dist: flake8-quotes (>=3.3.1,<4.0.0)
Requires-Dist: packaging (>=23.0,<24.0)
Requires-Dist: pydantic (>=2.7,<3.0)
Requires-Dist: python-dateutil (>=2.8.2,<3.0.0)
Requires-Dist: requests (>=2.27.1,<3.0.0)
Requires-Dist: requests-toolbelt (>=1.0.0,<2.0.0)
Requires-Dist: tenacity (>=8.1.0,!=8.4.0)
Requires-Dist: typing-extensions (>=4.6.1,<5.0.0)
Project-URL: Repository, https://github.com/cisco-en-programmability/catalystwan-sdk
